geoffreyplugins/__init__.py
geoffreyplugins/filesystem.py
geoffrey_filesystem-0.0.1.dist-info/DESCRIPTION.rst
geoffrey_filesystem-0.0.1.dist-info/RECORD
geoffrey_filesystem-0.0.1.dist-info/WHEEL
geoffrey_filesystem-0.0.1.dist-info/top_level.txt
geoffrey_filesystem-0.0.1.dist-info/metadata.json
geoffrey_filesystem-0.0.1.dist-info/METADATA
