Metadata-Version: 2.0
Name: geoffrey-filesystem
Version: 0.0.1
Summary: Read file changes in the local file system.
Home-page: https://github.com/nilp0inter/geoffrey-filesystem
Author: Roberto Abdelkader Martínez Pérez
Author-email: robertomartinezp@gmail.com
License: UNKNOWN
Platform: UNKNOWN
Requires-Dist: watchdog (>=0.7.1)
